LICENSE
README.md
setup.cfg
setup.py
naas_drivers/__init__.py
naas_drivers/driver.py
naas_drivers.egg-info/PKG-INFO
naas_drivers.egg-info/SOURCES.txt
naas_drivers.egg-info/dependency_links.txt
naas_drivers.egg-info/requires.txt
naas_drivers.egg-info/top_level.txt
naas_drivers/tools/__crud.py
naas_drivers/tools/__ftp.py
naas_drivers/tools/__ftps.py
naas_drivers/tools/__init__.py
naas_drivers/tools/airtable.py
naas_drivers/tools/awesomenotebook.py
naas_drivers/tools/bazimo.py
naas_drivers/tools/bigquery.py
naas_drivers/tools/bobapp.py
naas_drivers/tools/bubble.py
naas_drivers/tools/budgetinsight.py
naas_drivers/tools/canny.py
naas_drivers/tools/cityfalcon.py
naas_drivers/tools/email.py
naas_drivers/tools/emailbuilder.py
naas_drivers/tools/ftp.py
naas_drivers/tools/geolocator.py
naas_drivers/tools/git.py
naas_drivers/tools/github.py
naas_drivers/tools/googleanalytics.py
naas_drivers/tools/gsheet.py
naas_drivers/tools/healthcheck.py
naas_drivers/tools/hubspot.py
naas_drivers/tools/huggingface.py
naas_drivers/tools/ifttt.py
naas_drivers/tools/integromat.py
naas_drivers/tools/jupyter.py
naas_drivers/tools/linkedin.py
naas_drivers/tools/linkedin_salesnavigator.py
naas_drivers/tools/markdown.py
naas_drivers/tools/mongo.py
naas_drivers/tools/naas_auth.py
naas_drivers/tools/naas_chat_plugin.py
naas_drivers/tools/naas_credits.py
naas_drivers/tools/naas_events.py
naas_drivers/tools/newsapi.py
naas_drivers/tools/notion.py
naas_drivers/tools/optimise.py
naas_drivers/tools/pdf.py
naas_drivers/tools/plotly.py
naas_drivers/tools/prediction.py
naas_drivers/tools/qonto.py
naas_drivers/tools/sentiment.py
naas_drivers/tools/sharepoint.py
naas_drivers/tools/slack.py
naas_drivers/tools/snowflake.py
naas_drivers/tools/streamlit.py
naas_drivers/tools/taggun.py
naas_drivers/tools/teams.py
naas_drivers/tools/thinkific.py
naas_drivers/tools/toucan.py
naas_drivers/tools/twitter.py
naas_drivers/tools/utils.py
naas_drivers/tools/yahoofinance.py
naas_drivers/tools/youtube.py
naas_drivers/tools/zapier.py
tests/test_darkknight.py
tests/test_gsheet.py