Metadata-Version: 2.1
Name: naas-drivers
Version: 0.115.0
Summary: Drivers made to easy connect to any services
Home-page: https://github.com/jupyter-naas/drivers
Author: Maxime Jublou
Author-email: maxime@naas.ai
License: BSD
Classifier: Programming Language :: Python :: 3.8
Classifier: License :: OSI Approved :: BSD License
Classifier: Framework :: Jupyter
Classifier: Operating System :: OS Independent
Provides-Extra: dev
Provides-Extra: airtable
Provides-Extra: bigquery
Provides-Extra: email
Provides-Extra: ipython
Provides-Extra: emailbuilder
Provides-Extra: ftp
Provides-Extra: geolocator
Provides-Extra: git
Provides-Extra: google
Provides-Extra: markdown
Provides-Extra: mongo
Provides-Extra: naas_chat_plugin
Provides-Extra: newsapi
Provides-Extra: notion
Provides-Extra: plotly
Provides-Extra: cython
Provides-Extra: prediction
Provides-Extra: sentiment
Provides-Extra: slack
Provides-Extra: streamlit
Provides-Extra: teams
Provides-Extra: toucan
Provides-Extra: twitter
Provides-Extra: youtube
Provides-Extra: pydash
Provides-Extra: ml
Provides-Extra: sharepoint
Provides-Extra: snowflake
Provides-Extra: extra
Provides-Extra: full
Provides-Extra: fulldev
Provides-Extra: all
License-File: LICENSE
